hfydl/__main__.py
hfydl-0.0.1.dist-info/licenses/LICENSE
hfydl-0.0.1.dist-info/METADATA
hfydl-0.0.1.dist-info/WHEEL
hfydl-0.0.1.dist-info/entry_points.txt
hfydl-0.0.1.dist-info/top_level.txt
hfydl-0.0.1.dist-info/RECORD
