Metadata-Version: 2.4
Name: hfydl
Version: 0.0.1
Summary: Download and compile Reddit HFY stories into EPUB ebooks.
Author: Lizard Demon
License: GPL3
Requires-Python: >=3.6
License-File: LICENSE
Requires-Dist: requests
Requires-Dist: beautifulsoup4
Requires-Dist: pypandoc
Dynamic: license-file
